pysfpubsub/__init__.py
pysfpubsub/pubsub.py
pysfpubsub/pubsub_api_pb2.py
pysfpubsub/pubsub_api_pb2_grpc.py
pysfpubsub-0.1.2.dist-info/LICENSE
pysfpubsub-0.1.2.dist-info/METADATA
pysfpubsub-0.1.2.dist-info/WHEEL
pysfpubsub-0.1.2.dist-info/top_level.txt
pysfpubsub-0.1.2.dist-info/RECORD
