Metadata-Version: 2.1
Name: pysfpubsub
Version: 0.1.2
Summary: Python gRPC client for the Salesforce PubSub API.
Author-email: Benton Snyder <benton@bensnyde.me>
Project-URL: Homepage, https://github.com/bensnyde/pysfpubsub
Project-URL: Issues, https://github.com/bensnyde/pysfpubsub/issues
Classifier: Programming Language :: Python :: 3
Classifier: Operating System :: OS Independent
Requires-Python: >=3.8
License-File: LICENSE
